{
  "project": "servicesbg",
  "updated_at": "2026-06-25T23:07:49+03:00",
  "status": "crm_mvp_implemented",
  "production_modified": false,
  "application_code_written": true,
  "scope": "servicesbg_crm_mvp_only",
  "deliverables": [
    "app/wp-content/plugins/servicesbg-crm/",
    "docs/phase2g_crm_mvp_v1.md",
    "scripts/validate_crm_plugin.sh",
    "reports/latest.md",
    "reports/latest.json"
  ],
  "implemented_features": [
    "lead_schema",
    "customer_profile_schema",
    "customer_timeline_schema",
    "crm_note_schema",
    "followup_task_schema",
    "pipeline_item_schema",
    "lead_inquiry_creation",
    "customer_profile_creation",
    "customer_profile_timeline",
    "provider_customer_history",
    "crm_notes",
    "followup_tasks",
    "pipeline_status_tracking",
    "listing_linkage",
    "provider_linkage",
    "reservation_linkage",
    "review_linkage",
    "conversation_linkage",
    "claim_linkage",
    "admin_diagnostics_ui",
    "admin_capability",
    "wp_cli_crm_status",
    "wp_cli_crm_leads",
    "wp_cli_crm_lead_create",
    "wp_cli_crm_customer_profile",
    "wp_cli_crm_followup_create",
    "wp_cli_crm_create_test",
    "health_status_integration",
    "core_audit_integration",
    "runtime_validation_script"
  ],
  "schema": {
    "tables": [
      "wp_servicesbg_leads",
      "wp_servicesbg_customer_profiles",
      "wp_servicesbg_customer_timeline",
      "wp_servicesbg_crm_notes",
      "wp_servicesbg_followup_tasks",
      "wp_servicesbg_pipeline_items"
    ],
    "lead_statuses": [
      "new",
      "open",
      "contacted",
      "qualified",
      "converted",
      "lost",
      "archived"
    ],
    "pipeline_stages": [
      "new",
      "contacted",
      "qualified",
      "proposal",
      "booked",
      "won",
      "lost"
    ],
    "pipeline_statuses": [
      "open",
      "won",
      "lost",
      "archived"
    ]
  },
  "wp_cli": [
    "wp servicesbg crm status",
    "wp servicesbg crm leads",
    "wp servicesbg crm lead-create",
    "wp servicesbg crm customer-profile",
    "wp servicesbg crm followup-create",
    "wp servicesbg crm create-test"
  ],
  "validation": {
    "php_lint": "passed",
    "shell_syntax": "passed",
    "staging_activation": "passed",
    "staging_runtime_validation": "passed",
    "last_validated_at": "2026-06-25T23:07:49+03:00",
    "script": "scripts/validate_crm_plugin.sh",
    "wp_root": "/opt/projects/servicesbg/wp-staging",
    "checks": [
      "staging_database_connection",
      "servicesbg_crm_plugin_active",
      "wp_servicesbg_leads_table",
      "wp_servicesbg_customer_profiles_table",
      "wp_servicesbg_customer_timeline_table",
      "wp_servicesbg_crm_notes_table",
      "wp_servicesbg_followup_tasks_table",
      "wp_servicesbg_pipeline_items_table",
      "required_crm_columns",
      "admin_diagnostics_page_registration",
      "servicesbg_manage_crm_capability",
      "health_status_integration",
      "wp_cli_crm_status",
      "wp_cli_crm_leads",
      "wp_cli_crm_lead_create",
      "wp_cli_crm_customer_profile",
      "wp_cli_crm_followup_create",
      "wp_cli_crm_create_test",
      "lead_creation",
      "customer_profile_creation",
      "timeline_event_creation",
      "crm_note_creation",
      "followup_creation",
      "pipeline_status_update",
      "listing_provider_reservation_review_conversation_claim_linkage",
      "crm_audit_log_entries",
      "no_ai_automation_email_sms_push_external_api_payment_calendar_configuration"
    ]
  },
  "explicitly_not_implemented": [
    "ai_automation",
    "email_delivery",
    "sms_delivery",
    "push_notifications",
    "external_apis",
    "payments",
    "calendar_integrations"
  ],
  "rules_observed": {
    "no_tradingbot_context": true,
    "no_unai_context": true,
    "no_production_changes": true,
    "plugin_based_functionality": true,
    "no_business_logic_in_theme": true,
    "preserve_flynax_id_traceability_fields": true,
    "no_ai_automation": true,
    "no_email_delivery": true,
    "no_sms_delivery": true,
    "no_push_notifications": true,
    "no_external_apis": true,
    "no_payments": true,
    "no_calendar_integrations": true
  },
  "next_step": "Review CRM infrastructure MVP before approving AI automation, delivery integrations, payments, external APIs, or calendar integrations."
}
